[
  {
    "id": "HSH",
    "live": true,
    "logo": "/images/AcademiaLogoLong.png",
    "topBackgroundImage": "/images/HSHCover.png",
    "institutionCoursesUrl": "https://www.hsh.edu.au"
  },
  {
    "id": "academia",
    "logo": "/images/AcademiaLogoLong.png",
    "topBackgroundImage": "/images/AcademiaCover.jpeg",
    "institutionCoursesUrl": "https://www.studyacademia.edu.au"
  },
  {
    "id": "Blueprint Career Development",
    "live": true,
    "logo": "/images/AcademiaLogoLong.png",
    "topBackgroundImage": "/images/BlueprintCover.png",
    "institutionCoursesUrl": "https://www.blueprintcd.com.au/"
  },
  {
    "id": "Collarts",
    "logo": "/images/AcademiaLogoLong.png",
    "topBackgroundImage": "/images/CollartsCover.png",
    "institutionCoursesUrl": "https://www.collarts.edu.au/courses"
  },
  {
    "id": "Nepean Community College",
    "logo": "/images/AcademiaLogoLong.png",
    "topBackgroundImage": "/images/NepeanCover.png",
    "institutionCoursesUrl": "https://ncc.nsw.edu.au/our-courses/"
  }
]
